odoo9_addon_test_base_import_async-9.0.1.0.0.99.dev2-py2.7-nspkg.pth
odoo9_addon_test_base_import_async-9.0.1.0.0.99.dev2.dist-info/METADATA
odoo9_addon_test_base_import_async-9.0.1.0.0.99.dev2.dist-info/RECORD
odoo9_addon_test_base_import_async-9.0.1.0.0.99.dev2.dist-info/WHEEL
odoo9_addon_test_base_import_async-9.0.1.0.0.99.dev2.dist-info/namespace_packages.txt
odoo9_addon_test_base_import_async-9.0.1.0.0.99.dev2.dist-info/top_level.txt
odoo_addons/test_base_import_async/__init__.py
odoo_addons/test_base_import_async/__openerp__.py
odoo_addons/test_base_import_async/static/description/icon.png
odoo_addons/test_base_import_async/tests/__init__.py
odoo_addons/test_base_import_async/tests/account.move.csv
odoo_addons/test_base_import_async/tests/data.xml
odoo_addons/test_base_import_async/tests/test_base_import_async.py
